unimed_snowflake_common_functions/__init__.py
unimed_snowflake_common_functions/common_functions.py
unimed_snowflake_common_functions-0.0.1.dist-info/METADATA
unimed_snowflake_common_functions-0.0.1.dist-info/WHEEL
unimed_snowflake_common_functions-0.0.1.dist-info/licenses/LICENSE
unimed_snowflake_common_functions-0.0.1.dist-info/RECORD
