Metadata-Version: 2.3
Name: unimed_snowflake_common_functions
Version: 0.0.1
Summary: Snowflake Utility Functions
Project-URL: Homepage, https://unimed.co.nz
Author-email: Travis Hunting <travis.hunting@unimed.co.nz>
License-File: LICENSE
Classifier: License :: OSI Approved :: MIT License
Classifier: Operating System :: OS Independent
Classifier: Programming Language :: Python :: 3
Requires-Python: >=3.8
